pyNutri/__init__.py
pyNutri/pyNutri.py
PyNutri-1.3.dist-info/LICENSE
PyNutri-1.3.dist-info/METADATA
PyNutri-1.3.dist-info/WHEEL
PyNutri-1.3.dist-info/top_level.txt
PyNutri-1.3.dist-info/RECORD
