Metadata-Version: 2.1
Name: PyNutri
Version: 1.3
Summary: Pacote para suporte de cálculos relacionados a nutricao.
Author: Hudson Bandeira
Author-email: hudsonrb750@gmail.com
Classifier: Programming Language :: Python :: 3
Classifier: License :: OSI Approved :: MIT License
Classifier: Operating System :: OS Independent
Requires-Python: >=3.8
License-File: LICENSE
